pysislab/__init__.py
pysislab/cli.py
pysislab/get_sensors.py
pysislab/models.py
pysislab/tail.py
pysislab-0.0.7.dist-info/LICENSE
pysislab-0.0.7.dist-info/METADATA
pysislab-0.0.7.dist-info/WHEEL
pysislab-0.0.7.dist-info/entry_points.txt
pysislab-0.0.7.dist-info/top_level.txt
pysislab-0.0.7.dist-info/RECORD
