Metadata-Version: 2.1
Name: pysislab
Version: 0.0.7
Summary: Package to fetch data from the CRISiSLab seismometer network
Author: Ben Hong
Author-email: Ben Hong <benjamin.hong476@gmail.com>
Project-URL: Homepage, https://github.com/ben476/pysislab
Project-URL: Bug Tracker, https://github.com/ben476/pysislab/issues
Classifier: Development Status :: 3 - Alpha
Classifier: Intended Audience :: Developers
Classifier: Programming Language :: Python :: 3 :: Only
Classifier: Topic :: Software Development :: Libraries :: Python Modules
Classifier: Topic :: Utilities
Requires-Python: >=3.7
License-File: LICENSE
Requires-Dist: rich
Requires-Dist: requests
Requires-Dist: websocket-client
Requires-Dist: msgpack
Requires-Dist: pydantic
Requires-Dist: typeguard
